{
  "id": 11841,
  "user_id": 21271035,
  "cloneof_id": null,
  "string_id": "56684",
  "title": "Untitled",
  "description": "its a bit unfinish and it doesnt look good cause im not good a creating maps.",
  "data": "{\"screenObjects\":[{\"id\":1,\"type\":\"Hab\",\"layerId\":\"habitats\",\"points\":[{\"x\":0,\"y\":14.991},{\"x\":957.926,\"y\":14.991},{\"x\":957.926,\"y\":750},{\"x\":0,\"y\":750}],\"position\":{\"x\":0,\"y\":14.991},\"size\":{\"width\":957.926,\"height\":735.009},\"settings\":{\"area\":0}},{\"id\":2,\"type\":\"Hab\",\"layerId\":\"habitats\",\"points\":[{\"x\":2325.188,\"y\":16.753},{\"x\":3313.931,\"y\":16.753},{\"x\":3313.931,\"y\":750},{\"x\":2325.188,\"y\":750}],\"position\":{\"x\":2325.188,\"y\":16.753},\"size\":{\"width\":988.743,\"height\":733.247},\"settings\":{\"area\":0}},{\"id\":4,\"type\":\"Hab\",\"layerId\":\"habitats\",\"points\":[{\"x\":17.02,\"y\":33.454},{\"x\":3627.469,\"y\":33.454},{\"x\":3627.469,\"y\":750},{\"x\":17.02,\"y\":750}],\"position\":{\"x\":17.02,\"y\":33.454},\"size\":{\"width\":3610.449,\"height\":716.546},\"settings\":{\"area\":0}},{\"id\":5,\"type\":\"Hab\",\"layerId\":\"habitats\",\"points\":[{\"x\":4861.23,\"y\":20.043},{\"x\":5413.533,\"y\":20.043},{\"x\":5413.533,\"y\":348.89},{\"x\":4861.23,\"y\":348.89}],\"position\":{\"x\":4861.23,\"y\":20.043},\"size\":{\"width\":552.303,\"height\":328.847},\"settings\":{\"area\":0}},{\"id\":6,\"type\":\"Hab\",\"layerId\":\"habitats\",\"points\":[{\"x\":7114.335,\"y\":429.544},{\"x\":7670.87,\"y\":429.544},{\"x\":7670.87,\"y\":709.114},{\"x\":7114.335,\"y\":709.114}],\"position\":{\"x\":7114.335,\"y\":429.544},\"size\":{\"width\":556.535,\"height\":279.57},\"settings\":{\"area\":0}},{\"id\":7,\"type\":\"Hab\",\"layerId\":\"habitats\",\"points\":[{\"x\":6298.984,\"y\":23.283},{\"x\":7974.659,\"y\":23.283},{\"x\":7974.659,\"y\":726.136},{\"x\":6298.984,\"y\":726.136}],\"position\":{\"x\":6298.984,\"y\":23.283},\"size\":{\"width\":1675.675,\"height\":702.853},\"settings\":{\"area\":0}},{\"id\":14,\"type\":\"Wat\",\"layerId\":\"water\",\"points\":[{\"x\":31.531,\"y\":177.175},{\"x\":7998.551,\"y\":177.175},{\"x\":7998.551,\"y\":750},{\"x\":31.531,\"y\":750}],\"settings\":{\"collidable\":true},\"colors\":[14946,204080],\"hasBorder\":true},{\"id\":13,\"type\":\"Sky\",\"layerId\":\"sky\",\"points\":[{\"x\":11.953,\"y\":158.228},{\"x\":8000,\"y\":210.8},{\"x\":8000,\"y\":750},{\"x\":6.169,\"y\":745.236}],\"settings\":{\"collidable\":true},\"colors\":[13625852,8898552]},{\"id\":15,\"type\":\"Sky\",\"layerId\":\"sky\",\"points\":[{\"x\":13.595,\"y\":20.847},{\"x\":7989.786,\"y\":20.847},{\"x\":7989.786,\"y\":175.691},{\"x\":13.595,\"y\":175.691}],\"settings\":{\"collidable\":true},\"colors\":[13625852,8898552]}],\"settings\":{\"gravity\":9.8},\"worldSize\":{\"width\":800,\"height\":75}}",
  "public": true,
  "locked": false,
  "clonable": false,
  "permissions": 1,
  "likes": 1,
  "objects": 9,
  "created_at": "2023-03-01T04:13:55.000Z",
  "updated_at": "2023-03-01T04:16:42.000Z",
  "deleted_at": null,
  "user": {
    "id": 21271035,
    "username": "Ariette",
    "description": null,
    "about": null,
    "team_id": null,
    "team_role": null,
    "date_created": "2023-02-25T18:30:26.000Z",
    "date_last_played": "2023-05-24T02:20:43.000Z",
    "kill_count": 10,
    "play_count": 108,
    "highest_score": 325137,
    "picture": null,
    "displayPicture": true,
    "active": true,
    "ban_message": null,
    "ban_at": null,
    "coins": 34,
    "tier": 1,
    "xp": 3600,
    "migrated": false,
    "verified": false,
    "beta": false
  },
  "tags": [
    {
      "id": "000000"
    }
  ],
  "packs": [],
  "archived_at": "2025-04-23T23:18:46.572Z"
}