{
  "id": 252,
  "user_id": 594916,
  "cloneof_id": null,
  "string_id": "biome_battle",
  "title": "Biome Battle",
  "description": "Low effort map made in like ten minutes. gg yeet",
  "data": "{\"screenObjects\":[{\"id\":79,\"type\":\"Hab\",\"layerId\":\"habitats\",\"points\":[{\"x\":142.8,\"y\":195.807},{\"x\":426.568,\"y\":195.807},{\"x\":426.568,\"y\":460.657},{\"x\":142.8,\"y\":460.657}],\"position\":{\"x\":142.8,\"y\":195.807},\"size\":{\"width\":283.768,\"height\":264.85},\"settings\":{\"area\":39}},{\"id\":80,\"type\":\"Hab\",\"layerId\":\"habitats\",\"points\":[{\"x\":145.953,\"y\":630.287},{\"x\":427.199,\"y\":630.287},{\"x\":427.199,\"y\":897.029},{\"x\":145.953,\"y\":897.029}],\"position\":{\"x\":145.953,\"y\":630.287},\"size\":{\"width\":281.246,\"height\":266.742},\"settings\":{\"area\":37}},{\"id\":81,\"type\":\"Hab\",\"layerId\":\"habitats\",\"points\":[{\"x\":135.233,\"y\":1066.029},{\"x\":419.632,\"y\":1066.029},{\"x\":419.632,\"y\":1332.14},{\"x\":135.233,\"y\":1332.14}],\"position\":{\"x\":135.233,\"y\":1066.029},\"size\":{\"width\":284.399,\"height\":266.111},\"settings\":{\"area\":47}},{\"id\":82,\"type\":\"Hab\",\"layerId\":\"habitats\",\"points\":[{\"x\":642.862,\"y\":1065.398},{\"x\":927.891,\"y\":1065.398},{\"x\":927.891,\"y\":1332.14},{\"x\":642.862,\"y\":1332.14}],\"position\":{\"x\":642.862,\"y\":1065.398},\"size\":{\"width\":285.029,\"height\":266.742},\"settings\":{\"area\":42}},{\"id\":83,\"type\":\"Hab\",\"layerId\":\"habitats\",\"points\":[{\"x\":646.015,\"y\":621.459},{\"x\":929.152,\"y\":621.459},{\"x\":929.152,\"y\":890.093},{\"x\":646.015,\"y\":890.093}],\"position\":{\"x\":646.015,\"y\":621.459},\"size\":{\"width\":283.137,\"height\":268.634},\"settings\":{\"area\":63}},{\"id\":84,\"type\":\"Hab\",\"layerId\":\"habitats\",\"points\":[{\"x\":642.862,\"y\":182.564},{\"x\":927.891,\"y\":182.564},{\"x\":927.891,\"y\":449.937},{\"x\":642.862,\"y\":449.937}],\"position\":{\"x\":642.862,\"y\":182.564},\"size\":{\"width\":285.029,\"height\":267.373},\"settings\":{\"area\":38}},{\"id\":85,\"type\":\"Hab\",\"layerId\":\"habitats\",\"points\":[{\"x\":1074.19,\"y\":181.303},{\"x\":1359.219,\"y\":181.303},{\"x\":1359.219,\"y\":449.937},{\"x\":1074.19,\"y\":449.937}],\"position\":{\"x\":1074.19,\"y\":181.303},\"size\":{\"width\":285.029,\"height\":268.634},\"settings\":{\"area\":54}},{\"id\":86,\"type\":\"Hab\",\"layerId\":\"habitats\",\"points\":[{\"x\":1084.279,\"y\":624.612},{\"x\":1367.416,\"y\":624.612},{\"x\":1367.416,\"y\":891.354},{\"x\":1084.279,\"y\":891.354}],\"position\":{\"x\":1084.279,\"y\":624.612},\"size\":{\"width\":283.137,\"height\":266.742},\"settings\":{\"area\":22}},{\"id\":87,\"type\":\"Hab\",\"layerId\":\"habitats\",\"points\":[{\"x\":1064.1,\"y\":1067.921},{\"x\":1349.129,\"y\":1067.921},{\"x\":1349.129,\"y\":1334.663},{\"x\":1064.1,\"y\":1334.663}],\"position\":{\"x\":1064.1,\"y\":1067.921},\"size\":{\"width\":285.029,\"height\":266.742},\"settings\":{\"area\":62}},{\"id\":88,\"type\":\"Ter\",\"layerId\":\"terrains\",\"points\":[{\"x\":66.884,\"y\":59.162},{\"x\":1457.3,\"y\":54.89},{\"x\":1455.164,\"y\":1455.986},{\"x\":0,\"y\":1447.442},{\"x\":0,\"y\":1500},{\"x\":1500,\"y\":1500},{\"x\":1500,\"y\":0},{\"x\":0,\"y\":0},{\"x\":0,\"y\":1500},{\"x\":58.341,\"y\":1500}],\"texture\":\"assets/terrains/beach.png\"},{\"id\":116,\"type\":\"Ter\",\"layerId\":\"islands\",\"points\":[{\"x\":170.069,\"y\":627.175},{\"x\":226.192,\"y\":627.806},{\"x\":242.588,\"y\":638.526},{\"x\":218.625,\"y\":645.463},{\"x\":205.383,\"y\":656.813},{\"x\":190.879,\"y\":641.679},{\"x\":154.304,\"y\":637.265}],\"texture\":\"assets/terrains/glacier.png\"},{\"id\":117,\"type\":\"Ter\",\"layerId\":\"islands\",\"points\":[{\"x\":339.7,\"y\":639.157},{\"x\":363.032,\"y\":648.616},{\"x\":385.102,\"y\":661.228},{\"x\":399.606,\"y\":641.049},{\"x\":421.046,\"y\":636.004},{\"x\":405.912,\"y\":626.545},{\"x\":354.203,\"y\":626.545}],\"texture\":\"assets/terrains/glacier.png\"},{\"id\":122,\"type\":\"Ter\",\"layerId\":\"islands\",\"points\":[{\"x\":1265.63,\"y\":840.449},{\"x\":1283.991,\"y\":840.449},{\"x\":1316.308,\"y\":840.449},{\"x\":1334.67,\"y\":826.494},{\"x\":1357.439,\"y\":821.352},{\"x\":1368.898,\"y\":821.646},{\"x\":1401.847,\"y\":788.885},{\"x\":1303.822,\"y\":799.318},{\"x\":1289.133,\"y\":818.414},{\"x\":1259.754,\"y\":819.149},{\"x\":1231.844,\"y\":839.714}],\"texture\":\"assets/terrains/swamp/island.png\"},{\"id\":123,\"type\":\"Ter\",\"layerId\":\"islands\",\"points\":[{\"x\":1107.561,\"y\":617.233},{\"x\":1182.291,\"y\":615.24},{\"x\":1208.197,\"y\":633.176},{\"x\":1188.269,\"y\":639.154},{\"x\":1162.363,\"y\":650.114},{\"x\":1147.417,\"y\":642.143},{\"x\":1127.489,\"y\":641.147},{\"x\":1105.568,\"y\":651.111},{\"x\":1088.63,\"y\":639.154},{\"x\":1075.676,\"y\":639.154},{\"x\":1083.648,\"y\":618.23}],\"texture\":\"assets/terrains/swamp/island.png\"},{\"id\":124,\"type\":\"Ter\",\"layerId\":\"islands\",\"points\":[{\"x\":1241.525,\"y\":644.02},{\"x\":1294.909,\"y\":638.217},{\"x\":1309.996,\"y\":650.983},{\"x\":1333.207,\"y\":650.983},{\"x\":1351.775,\"y\":646.341},{\"x\":1370.344,\"y\":640.538},{\"x\":1380.789,\"y\":650.983},{\"x\":1387.752,\"y\":668.391},{\"x\":1400.518,\"y\":659.107},{\"x\":1401.678,\"y\":640.538},{\"x\":1397.036,\"y\":628.933},{\"x\":1376.146,\"y\":620.809},{\"x\":1347.133,\"y\":615.007},{\"x\":1305.354,\"y\":619.649},{\"x\":1274.02,\"y\":625.451}],\"texture\":\"assets/terrains/swamp/island.png\"},{\"id\":125,\"type\":\"Ter\",\"layerId\":\"islands\",\"points\":[{\"x\":1258.666,\"y\":894.279},{\"x\":1266.569,\"y\":895.208},{\"x\":1287.021,\"y\":906.364},{\"x\":1336.759,\"y\":901.716},{\"x\":1362.324,\"y\":894.279},{\"x\":1380.918,\"y\":896.603},{\"x\":1394.398,\"y\":888.701},{\"x\":1417.64,\"y\":869.177},{\"x\":1425.542,\"y\":850.584},{\"x\":1400.441,\"y\":853.838},{\"x\":1379.988,\"y\":854.768},{\"x\":1357.211,\"y\":863.599},{\"x\":1339.083,\"y\":873.826},{\"x\":1313.517,\"y\":873.361},{\"x\":1300.501,\"y\":861.275},{\"x\":1281.908,\"y\":861.275},{\"x\":1261.92,\"y\":874.291}],\"texture\":\"assets/terrains/swamp/island.png\"},{\"id\":126,\"type\":\"Ter\",\"layerId\":\"islands\",\"points\":[{\"x\":1209.086,\"y\":892.157},{\"x\":1194.468,\"y\":895.406},{\"x\":1138.162,\"y\":902.444},{\"x\":1096.474,\"y\":893.475},{\"x\":1079.838,\"y\":895.876},{\"x\":1080.773,\"y\":867.252},{\"x\":1043.416,\"y\":844.513},{\"x\":1064.531,\"y\":841.806},{\"x\":1077.831,\"y\":840.953},{\"x\":1081.309,\"y\":824.624},{\"x\":1080.921,\"y\":801.895},{\"x\":1100.805,\"y\":797.411},{\"x\":1134.372,\"y\":809.863},{\"x\":1149.532,\"y\":842.348},{\"x\":1186.889,\"y\":848.303},{\"x\":1208.004,\"y\":876.456}],\"texture\":\"assets/terrains/swamp/island.png\"},{\"id\":127,\"type\":\"Ter\",\"layerId\":\"islands\",\"points\":[{\"x\":640.567,\"y\":1282.241},{\"x\":639.484,\"y\":1328.802},{\"x\":656.268,\"y\":1346.668},{\"x\":722.861,\"y\":1364.535},{\"x\":784.04,\"y\":1354.79},{\"x\":809.486,\"y\":1342.879},{\"x\":843.595,\"y\":1358.579},{\"x\":862.002,\"y\":1376.987},{\"x\":879.869,\"y\":1362.369},{\"x\":905.856,\"y\":1346.127},{\"x\":933.468,\"y\":1333.675},{\"x\":931.303,\"y\":1303.356},{\"x\":928.596,\"y\":1284.407},{\"x\":915.06,\"y\":1272.496},{\"x\":892.321,\"y\":1267.082},{\"x\":869.041,\"y\":1269.247},{\"x\":857.13,\"y\":1287.655},{\"x\":849.55,\"y\":1309.311},{\"x\":832.766,\"y\":1313.101},{\"x\":818.148,\"y\":1309.311},{\"x\":797.083,\"y\":1302.185},{\"x\":783.115,\"y\":1305.378},{\"x\":774.335,\"y\":1293.405},{\"x\":778.725,\"y\":1276.245},{\"x\":797.881,\"y\":1269.46},{\"x\":828.611,\"y\":1267.864},{\"x\":829.01,\"y\":1255.492},{\"x\":803.07,\"y\":1249.506},{\"x\":780.752,\"y\":1249.467},{\"x\":749.892,\"y\":1258.671},{\"x\":726.612,\"y\":1260.295},{\"x\":716.866,\"y\":1279.244},{\"x\":709.287,\"y\":1298.194},{\"x\":695.751,\"y\":1298.194},{\"x\":691.42,\"y\":1286.283},{\"x\":690.337,\"y\":1265.168},{\"x\":669.764,\"y\":1255.422},{\"x\":644.859,\"y\":1259.212},{\"x\":637.279,\"y\":1266.251}],\"texture\":\"assets/terrains/deepterrain.png\"},{\"id\":128,\"type\":\"Ter\",\"layerId\":\"islands\",\"points\":[{\"x\":643,\"y\":1184.711},{\"x\":636.503,\"y\":1170.635},{\"x\":634.879,\"y\":1146.813},{\"x\":638.668,\"y\":1128.405},{\"x\":648.955,\"y\":1126.239},{\"x\":680.898,\"y\":1128.405},{\"x\":699.848,\"y\":1141.399},{\"x\":723.128,\"y\":1168.469},{\"x\":736.122,\"y\":1187.96},{\"x\":704.179,\"y\":1189.584},{\"x\":675.484,\"y\":1184.17}],\"texture\":\"assets/terrains/deepterrain.png\"},{\"id\":129,\"type\":\"Ter\",\"layerId\":\"islands\",\"points\":[{\"x\":789.18,\"y\":1176.59},{\"x\":789.18,\"y\":1157.1},{\"x\":796.76,\"y\":1130.571},{\"x\":816.792,\"y\":1118.66},{\"x\":843.321,\"y\":1107.832},{\"x\":879.053,\"y\":1112.163},{\"x\":890.423,\"y\":1146.272},{\"x\":894.754,\"y\":1174.425},{\"x\":884.468,\"y\":1187.419},{\"x\":860.104,\"y\":1186.877},{\"x\":863.894,\"y\":1157.1},{\"x\":850.9,\"y\":1135.443},{\"x\":829.244,\"y\":1135.443},{\"x\":816.25,\"y\":1154.393},{\"x\":816.25,\"y\":1176.59},{\"x\":804.339,\"y\":1182.546}],\"texture\":\"assets/terrains/deepterrain.png\"},{\"id\":130,\"type\":\"Ter\",\"layerId\":\"islands\",\"points\":[{\"x\":642.458,\"y\":1095.921},{\"x\":640.834,\"y\":1075.347},{\"x\":645.707,\"y\":1058.563},{\"x\":668.987,\"y\":1056.398},{\"x\":699.306,\"y\":1061.812},{\"x\":730.708,\"y\":1061.812},{\"x\":745.867,\"y\":1059.646},{\"x\":755.613,\"y\":1076.971},{\"x\":757.778,\"y\":1091.048},{\"x\":758.861,\"y\":1113.787},{\"x\":751.823,\"y\":1134.361},{\"x\":741.536,\"y\":1132.736},{\"x\":735.58,\"y\":1118.66},{\"x\":724.752,\"y\":1094.296},{\"x\":698.223,\"y\":1086.175},{\"x\":669.529,\"y\":1089.965},{\"x\":650.579,\"y\":1100.252}],\"texture\":\"assets/terrains/deepterrain.png\"},{\"id\":131,\"type\":\"Ter\",\"layerId\":\"islands\",\"points\":[{\"x\":815.167,\"y\":1074.264},{\"x\":843.862,\"y\":1074.264},{\"x\":870.391,\"y\":1075.889},{\"x\":879.053,\"y\":1071.016},{\"x\":877.429,\"y\":1063.978},{\"x\":860.646,\"y\":1061.271},{\"x\":835.741,\"y\":1057.481},{\"x\":816.25,\"y\":1060.188},{\"x\":804.881,\"y\":1070.474}],\"texture\":\"assets/terrains/deepterrain.png\"},{\"id\":132,\"type\":\"Ter\",\"layerId\":\"islands\",\"points\":[{\"x\":921.825,\"y\":1141.399},{\"x\":926.156,\"y\":1157.1},{\"x\":933.736,\"y\":1152.227},{\"x\":936.984,\"y\":1131.112},{\"x\":932.653,\"y\":1107.29},{\"x\":925.615,\"y\":1096.462},{\"x\":916.952,\"y\":1095.921},{\"x\":914.245,\"y\":1108.373}],\"texture\":\"assets/terrains/deepterrain.png\"},{\"id\":133,\"type\":\"Ter\",\"layerId\":\"islands\",\"points\":[{\"x\":928.863,\"y\":1220.444},{\"x\":922.908,\"y\":1230.731},{\"x\":922.366,\"y\":1251.305},{\"x\":928.322,\"y\":1253.47},{\"x\":931.57,\"y\":1237.769}],\"texture\":\"assets/terrains/deepterrain.png\"},{\"id\":134,\"type\":\"Ter\",\"layerId\":\"islands\",\"points\":[{\"x\":704.179,\"y\":1221.527},{\"x\":732.873,\"y\":1227.483},{\"x\":740.453,\"y\":1225.317},{\"x\":733.415,\"y\":1218.82},{\"x\":720.421,\"y\":1217.196}],\"texture\":\"assets/terrains/deepterrain.png\"},{\"id\":135,\"type\":\"Ter\",\"layerId\":\"islands\",\"points\":[{\"x\":837.906,\"y\":1223.151},{\"x\":854.149,\"y\":1226.4},{\"x\":855.232,\"y\":1220.444},{\"x\":843.862,\"y\":1218.279},{\"x\":828.161,\"y\":1218.82}],\"texture\":\"assets/terrains/deepterrain.png\"},{\"id\":136,\"type\":\"Ter\",\"layerId\":\"islands\",\"points\":[{\"x\":303.121,\"y\":901.772},{\"x\":341.587,\"y\":907.447},{\"x\":371.855,\"y\":920.059},{\"x\":413.475,\"y\":900.511},{\"x\":433.023,\"y\":896.727},{\"x\":445.635,\"y\":879.701},{\"x\":473.381,\"y\":863.306},{\"x\":495.452,\"y\":857.63},{\"x\":483.471,\"y\":843.127},{\"x\":456.355,\"y\":842.496},{\"x\":442.482,\"y\":845.649},{\"x\":428.609,\"y\":839.343},{\"x\":430.501,\"y\":817.272},{\"x\":395.818,\"y\":823.578},{\"x\":375.639,\"y\":831.145},{\"x\":361.766,\"y\":840.604},{\"x\":342.848,\"y\":846.91},{\"x\":323.3,\"y\":858.261},{\"x\":311.949,\"y\":870.242},{\"x\":298.706,\"y\":887.899}],\"texture\":\"assets/terrains/coldterrain.png\"},{\"id\":137,\"type\":\"Ter\",\"layerId\":\"islands\",\"points\":[{\"x\":145.472,\"y\":858.891},{\"x\":110.158,\"y\":865.197},{\"x\":84.934,\"y\":861.414},{\"x\":93.132,\"y\":881.593},{\"x\":123.401,\"y\":903.033},{\"x\":153.669,\"y\":906.186},{\"x\":197.18,\"y\":908.709},{\"x\":227.449,\"y\":898.619},{\"x\":253.934,\"y\":896.097},{\"x\":245.736,\"y\":885.376},{\"x\":226.818,\"y\":873.395},{\"x\":194.027,\"y\":867.72},{\"x\":175.11,\"y\":877.809},{\"x\":154.931,\"y\":871.503}],\"texture\":\"assets/terrains/coldterrain.png\"},{\"id\":138,\"type\":\"Ter\",\"layerId\":\"islands\",\"points\":[{\"x\":145.472,\"y\":819.794},{\"x\":163.128,\"y\":811.597},{\"x\":186.46,\"y\":805.291},{\"x\":195.919,\"y\":790.787},{\"x\":191.505,\"y\":775.653},{\"x\":170.065,\"y\":769.347},{\"x\":147.994,\"y\":761.78},{\"x\":132.86,\"y\":759.888},{\"x\":108.897,\"y\":759.888},{\"x\":91.871,\"y\":772.5},{\"x\":105.744,\"y\":786.373},{\"x\":135.382,\"y\":817.903}],\"texture\":\"assets/terrains/coldterrain.png\"},{\"id\":139,\"type\":\"Ter\",\"layerId\":\"islands\",\"points\":[{\"x\":415.018,\"y\":661.152},{\"x\":442.193,\"y\":660.418},{\"x\":467.9,\"y\":669.966},{\"x\":458.352,\"y\":682.452},{\"x\":436.318,\"y\":678.779},{\"x\":416.487,\"y\":677.31},{\"x\":401.797,\"y\":682.452}],\"texture\":\"assets/terrains/glacier.png\"},{\"id\":140,\"type\":\"Ter\",\"layerId\":\"islands\",\"points\":[{\"x\":152.075,\"y\":666.293},{\"x\":164.561,\"y\":672.169},{\"x\":155.748,\"y\":689.062},{\"x\":140.324,\"y\":684.655},{\"x\":121.227,\"y\":674.373},{\"x\":105.069,\"y\":673.638},{\"x\":124.165,\"y\":656.745},{\"x\":140.324,\"y\":660.418},{\"x\":147.669,\"y\":664.09}],\"texture\":\"assets/terrains/glacier.png\"},{\"id\":141,\"type\":\"Ter\",\"layerId\":\"islands\",\"points\":[{\"x\":806.183,\"y\":450.497},{\"x\":837.043,\"y\":456.994},{\"x\":877.107,\"y\":461.326},{\"x\":886.852,\"y\":473.237},{\"x\":878.19,\"y\":484.606},{\"x\":863.572,\"y\":493.81},{\"x\":848.413,\"y\":498.141},{\"x\":827.839,\"y\":499.224},{\"x\":810.514,\"y\":499.766},{\"x\":804.559,\"y\":504.097},{\"x\":805.1,\"y\":516.008},{\"x\":815.928,\"y\":524.129},{\"x\":842.457,\"y\":524.129},{\"x\":884.687,\"y\":519.798},{\"x\":899.305,\"y\":536.581},{\"x\":926.917,\"y\":516.549},{\"x\":937.203,\"y\":492.186},{\"x\":938.828,\"y\":456.453},{\"x\":927.458,\"y\":448.332},{\"x\":928.541,\"y\":423.427},{\"x\":938.286,\"y\":405.561},{\"x\":943.159,\"y\":364.414},{\"x\":966.439,\"y\":335.719},{\"x\":924.21,\"y\":335.719},{\"x\":911.757,\"y\":338.968},{\"x\":894.974,\"y\":346.547},{\"x\":877.649,\"y\":341.133},{\"x\":861.948,\"y\":339.509},{\"x\":846.247,\"y\":342.216},{\"x\":830.005,\"y\":344.923},{\"x\":819.718,\"y\":362.789},{\"x\":808.348,\"y\":404.478}],\"texture\":\"assets/terrains/terrain.png\"},{\"id\":142,\"type\":\"Ter\",\"layerId\":\"islands\",\"points\":[{\"x\":799.686,\"y\":266.419},{\"x\":834.336,\"y\":279.413},{\"x\":873.317,\"y\":273.457},{\"x\":904.719,\"y\":260.463},{\"x\":920.961,\"y\":244.221},{\"x\":897.139,\"y\":229.062},{\"x\":863.572,\"y\":218.775},{\"x\":835.96,\"y\":228.52},{\"x\":805.641,\"y\":231.227},{\"x\":780.737,\"y\":222.023},{\"x\":757.997,\"y\":220.399},{\"x\":742.297,\"y\":236.641},{\"x\":741.755,\"y\":261.005},{\"x\":759.08,\"y\":272.374},{\"x\":781.278,\"y\":276.164}],\"texture\":\"assets/terrains/terrain.png\"},{\"id\":144,\"type\":\"Ter\",\"layerId\":\"islands\",\"points\":[{\"x\":1060.421,\"y\":677.194},{\"x\":1048.8,\"y\":679.053},{\"x\":1022.304,\"y\":678.124},{\"x\":1022.769,\"y\":687.885},{\"x\":1053.448,\"y\":693.928},{\"x\":1075.295,\"y\":696.717},{\"x\":1094.819,\"y\":702.76},{\"x\":1107.834,\"y\":690.674},{\"x\":1088.776,\"y\":679.518}],\"texture\":\"assets/terrains/swamp/island.png\"},{\"id\":145,\"type\":\"Ter\",\"layerId\":\"islands\",\"points\":[{\"x\":1346.294,\"y\":694.393},{\"x\":1377.438,\"y\":690.209},{\"x\":1397.425,\"y\":695.788},{\"x\":1403.003,\"y\":710.197},{\"x\":1376.043,\"y\":712.522},{\"x\":1343.505,\"y\":709.733},{\"x\":1328.165,\"y\":698.577},{\"x\":1337.927,\"y\":694.858}],\"texture\":\"assets/terrains/swamp/island.png\"},{\"id\":146,\"type\":\"Ter\",\"layerId\":\"islands\",\"points\":[{\"x\":650.656,\"y\":188.911},{\"x\":681.335,\"y\":191.235},{\"x\":694.351,\"y\":203.321},{\"x\":715.733,\"y\":206.11},{\"x\":731.073,\"y\":200.997},{\"x\":743.623,\"y\":187.517},{\"x\":757.103,\"y\":185.193},{\"x\":734.326,\"y\":180.079},{\"x\":703.647,\"y\":175.896},{\"x\":676.222,\"y\":179.615}],\"texture\":\"assets/terrains/beach.png\"},{\"id\":147,\"type\":\"Ter\",\"layerId\":\"islands\",\"points\":[{\"x\":861.691,\"y\":189.376},{\"x\":890.975,\"y\":189.841},{\"x\":903.061,\"y\":198.673},{\"x\":918.865,\"y\":198.673},{\"x\":929.092,\"y\":195.884},{\"x\":945.361,\"y\":189.841},{\"x\":967.733,\"y\":184.722},{\"x\":1004.571,\"y\":176.126},{\"x\":945.826,\"y\":169.388},{\"x\":922.584,\"y\":172.177},{\"x\":891.44,\"y\":176.826}],\"texture\":\"assets/terrains/beach.png\"},{\"id\":148,\"type\":\"Ter\",\"layerId\":\"islands\",\"points\":[{\"x\":658.817,\"y\":630.44},{\"x\":690.977,\"y\":636.746},{\"x\":718.723,\"y\":646.205},{\"x\":743.947,\"y\":636.115},{\"x\":759.712,\"y\":629.179},{\"x\":737.011,\"y\":615.936},{\"x\":697.283,\"y\":609.63},{\"x\":673.32,\"y\":615.306}],\"texture\":\"assets/terrains/beach.png\"},{\"id\":149,\"type\":\"Ter\",\"layerId\":\"islands\",\"points\":[{\"x\":850.518,\"y\":632.332},{\"x\":875.742,\"y\":636.115},{\"x\":895.169,\"y\":626.282},{\"x\":938.718,\"y\":622.916},{\"x\":910.424,\"y\":615.306},{\"x\":873.85,\"y\":616.567},{\"x\":854.301,\"y\":619.72},{\"x\":830.969,\"y\":628.548}],\"texture\":\"assets/terrains/beach.png\"},{\"id\":150,\"type\":\"Ter\",\"layerId\":\"islands\",\"points\":[{\"x\":648.877,\"y\":720.663},{\"x\":601.929,\"y\":723.452},{\"x\":614.944,\"y\":717.409},{\"x\":625.635,\"y\":714.155},{\"x\":637.256,\"y\":709.972},{\"x\":645.158,\"y\":700.675},{\"x\":643.764,\"y\":689.519},{\"x\":641.904,\"y\":676.968},{\"x\":650.271,\"y\":673.715},{\"x\":670.724,\"y\":673.715},{\"x\":692.106,\"y\":683.476},{\"x\":702.798,\"y\":707.647},{\"x\":688.388,\"y\":712.761},{\"x\":674.443,\"y\":705.323},{\"x\":661.892,\"y\":712.296},{\"x\":677.697,\"y\":723.917},{\"x\":672.119,\"y\":732.749}],\"texture\":\"assets/terrains/coldterrain.png\"},{\"id\":151,\"type\":\"Ter\",\"layerId\":\"islands\",\"points\":[{\"x\":639.58,\"y\":766.217},{\"x\":656.314,\"y\":766.217},{\"x\":678.626,\"y\":776.443},{\"x\":687.458,\"y\":786.669},{\"x\":682.81,\"y\":796.896},{\"x\":674.443,\"y\":815.489},{\"x\":682.81,\"y\":826.645},{\"x\":673.048,\"y\":836.871},{\"x\":650.736,\"y\":838.731},{\"x\":637.721,\"y\":828.504},{\"x\":634.467,\"y\":811.77},{\"x\":643.299,\"y\":784.345}],\"texture\":\"assets/terrains/coldterrain.png\"},{\"id\":152,\"type\":\"Ter\",\"layerId\":\"islands\",\"points\":[{\"x\":700.474,\"y\":820.137},{\"x\":695.825,\"y\":810.376},{\"x\":706.981,\"y\":797.825},{\"x\":737.195,\"y\":811.77},{\"x\":722.321,\"y\":826.645},{\"x\":704.192,\"y\":836.871}],\"texture\":\"assets/terrains/glacier.png\"},{\"id\":153,\"type\":\"Ter\",\"layerId\":\"islands\",\"points\":[{\"x\":700.938,\"y\":736.467},{\"x\":711.63,\"y\":725.311},{\"x\":723.715,\"y\":731.354},{\"x\":712.559,\"y\":743.44},{\"x\":703.263,\"y\":744.369}],\"texture\":\"assets/terrains/glacier.png\"},{\"id\":154,\"type\":\"Ter\",\"layerId\":\"islands\",\"points\":[{\"x\":922.389,\"y\":763.878},{\"x\":945.158,\"y\":763.878},{\"x\":937.813,\"y\":778.567},{\"x\":928.999,\"y\":799.133},{\"x\":928.265,\"y\":821.167},{\"x\":916.513,\"y\":830.715},{\"x\":893.744,\"y\":839.529},{\"x\":871.71,\"y\":826.308},{\"x\":852.614,\"y\":796.195},{\"x\":864.365,\"y\":785.912},{\"x\":908.434,\"y\":790.319}],\"texture\":\"assets/terrains/swamp/island.png\"},{\"id\":155,\"type\":\"Ter\",\"layerId\":\"islands\",\"points\":[{\"x\":929.734,\"y\":722.013},{\"x\":909.168,\"y\":722.013},{\"x\":890.072,\"y\":730.826},{\"x\":855.551,\"y\":727.888},{\"x\":842.331,\"y\":708.058},{\"x\":869.506,\"y\":695.571},{\"x\":895.948,\"y\":691.899},{\"x\":913.575,\"y\":671.334},{\"x\":926.061,\"y\":674.272},{\"x\":932.671,\"y\":676.475}],\"texture\":\"assets/terrains/swamp/island.png\"},{\"id\":156,\"type\":\"Ter\",\"layerId\":\"islands\",\"points\":[{\"x\":928.999,\"y\":859.36},{\"x\":954.706,\"y\":863.766},{\"x\":971.599,\"y\":862.298},{\"x\":969.395,\"y\":880.659},{\"x\":947.361,\"y\":880.659},{\"x\":932.671,\"y\":888.739},{\"x\":915.044,\"y\":894.614},{\"x\":890.072,\"y\":894.614},{\"x\":880.524,\"y\":874.784}],\"texture\":\"assets/terrains/swamp/island.png\"},{\"id\":157,\"type\":\"Ter\",\"layerId\":\"islands\",\"points\":[{\"x\":887.134,\"y\":758.002},{\"x\":873.179,\"y\":758.002},{\"x\":881.993,\"y\":753.595}],\"texture\":\"assets/terrains/swamp/island.png\"},{\"id\":158,\"type\":\"Ter\",\"layerId\":\"islands\",\"points\":[{\"x\":863.405,\"y\":670.102},{\"x\":879.105,\"y\":670.102},{\"x\":860.698,\"y\":679.847},{\"x\":834.71,\"y\":680.388}],\"texture\":\"assets/terrains/swamp/island.png\"},{\"id\":159,\"type\":\"Ter\",\"layerId\":\"islands\",\"points\":[{\"x\":755.458,\"y\":891.298},{\"x\":737.171,\"y\":893.82},{\"x\":687.984,\"y\":900.757},{\"x\":656.454,\"y\":897.604},{\"x\":636.275,\"y\":889.406},{\"x\":650.148,\"y\":873.641},{\"x\":692.398,\"y\":867.966},{\"x\":718.883,\"y\":867.966},{\"x\":745.368,\"y\":853.462},{\"x\":761.133,\"y\":843.373},{\"x\":768.07,\"y\":865.443}],\"texture\":\"assets/terrains/deepterrain.png\"},{\"id\":160,\"type\":\"Ter\",\"layerId\":\"islands\",\"points\":[{\"x\":802.29,\"y\":891.529},{\"x\":836.342,\"y\":893.421},{\"x\":864.088,\"y\":893.421},{\"x\":859.043,\"y\":880.179},{\"x\":842.017,\"y\":856.216},{\"x\":824.991,\"y\":856.216},{\"x\":802.92,\"y\":833.515},{\"x\":808.595,\"y\":860},{\"x\":802.29,\"y\":873.242}],\"texture\":\"assets/terrains/deepterrain.png\"},{\"id\":162,\"type\":\"Ter\",\"layerId\":\"islands\",\"points\":[{\"x\":757.371,\"y\":658.585},{\"x\":787.702,\"y\":658.186},{\"x\":806.46,\"y\":651.401},{\"x\":830.006,\"y\":656.19},{\"x\":814.84,\"y\":671.356},{\"x\":780.519,\"y\":682.929},{\"x\":752.183,\"y\":688.517},{\"x\":722.252,\"y\":682.131}],\"texture\":\"assets/terrains/terrain.png\"},{\"id\":163,\"type\":\"Ter\",\"layerId\":\"islands\",\"points\":[{\"x\":426.387,\"y\":348.229},{\"x\":402.016,\"y\":359.834},{\"x\":369.521,\"y\":356.352},{\"x\":350.952,\"y\":356.352},{\"x\":313.815,\"y\":363.316},{\"x\":294.086,\"y\":391.168},{\"x\":291.765,\"y\":423.663},{\"x\":291.765,\"y\":461.961},{\"x\":333.544,\"y\":471.245},{\"x\":384.608,\"y\":471.245},{\"x\":418.263,\"y\":479.369},{\"x\":431.029,\"y\":493.295},{\"x\":477.451,\"y\":499.098},{\"x\":483.253,\"y\":474.727},{\"x\":460.043,\"y\":468.924},{\"x\":439.153,\"y\":461.961},{\"x\":429.869,\"y\":441.071},{\"x\":439.153,\"y\":412.058},{\"x\":471.648,\"y\":403.934},{\"x\":490.216,\"y\":390.008},{\"x\":480.587,\"y\":370.729},{\"x\":482.093,\"y\":348.229}],\"texture\":\"assets/terrains/terrain.png\"},{\"id\":164,\"type\":\"Ter\",\"layerId\":\"islands\",\"points\":[{\"x\":426.527,\"y\":262.617},{\"x\":417.698,\"y\":255.68},{\"x\":412.654,\"y\":233.609},{\"x\":400.042,\"y\":219.106},{\"x\":370.404,\"y\":205.863},{\"x\":336.351,\"y\":205.233},{\"x\":350.225,\"y\":191.99},{\"x\":383.016,\"y\":186.945},{\"x\":418.329,\"y\":186.945},{\"x\":435.355,\"y\":197.035},{\"x\":436.616,\"y\":214.691},{\"x\":431.571,\"y\":233.609},{\"x\":440.4,\"y\":247.482},{\"x\":454.903,\"y\":250.635},{\"x\":475.713,\"y\":251.266},{\"x\":460.579,\"y\":261.986},{\"x\":443.553,\"y\":263.878}],\"texture\":\"assets/terrains/beach.png\"},{\"id\":165,\"type\":\"Ter\",\"layerId\":\"islands\",\"points\":[{\"x\":246.176,\"y\":462.516},{\"x\":246.807,\"y\":448.643},{\"x\":237.979,\"y\":433.508},{\"x\":215.277,\"y\":426.572},{\"x\":191.314,\"y\":430.355},{\"x\":159.785,\"y\":430.355},{\"x\":150.326,\"y\":407.023},{\"x\":149.695,\"y\":379.908},{\"x\":161.676,\"y\":358.467},{\"x\":149.695,\"y\":330.721},{\"x\":125.732,\"y\":330.721},{\"x\":123.21,\"y\":375.493},{\"x\":113.751,\"y\":393.781},{\"x\":123.841,\"y\":429.725},{\"x\":130.147,\"y\":466.93},{\"x\":170.505,\"y\":478.281},{\"x\":196.359,\"y\":493.415},{\"x\":197.62,\"y\":509.18},{\"x\":208.971,\"y\":490.262},{\"x\":237.348,\"y\":477.65}],\"texture\":\"assets/terrains/coldterrain.png\"},{\"id\":166,\"type\":\"Ter\",\"layerId\":\"islands\",\"points\":[{\"x\":142.759,\"y\":215.953},{\"x\":153.479,\"y\":222.259},{\"x\":168.613,\"y\":215.322},{\"x\":183.117,\"y\":222.259},{\"x\":204.557,\"y\":212.8},{\"x\":222.214,\"y\":218.475},{\"x\":240.501,\"y\":207.124},{\"x\":232.934,\"y\":196.404},{\"x\":220.322,\"y\":191.359},{\"x\":204.557,\"y\":188.837},{\"x\":192.576,\"y\":178.117},{\"x\":187.531,\"y\":162.352},{\"x\":188.161,\"y\":139.02},{\"x\":174.919,\"y\":154.154},{\"x\":167.982,\"y\":169.289},{\"x\":173.027,\"y\":178.748},{\"x\":166.721,\"y\":185.053},{\"x\":154.109,\"y\":188.837},{\"x\":140.867,\"y\":191.99},{\"x\":130.777,\"y\":205.233}],\"texture\":\"assets/terrains/glacier.png\"},{\"id\":167,\"type\":\"Ter\",\"layerId\":\"islands\",\"points\":[{\"x\":218.925,\"y\":391.792},{\"x\":195.422,\"y\":387.385},{\"x\":199.829,\"y\":360.21},{\"x\":227.004,\"y\":362.413},{\"x\":229.942,\"y\":377.837}],\"texture\":\"assets/terrains/coldterrain.png\"},{\"id\":168,\"type\":\"Ter\",\"layerId\":\"islands\",\"points\":[{\"x\":420.559,\"y\":1189.146},{\"x\":402.931,\"y\":1189.146},{\"x\":390.268,\"y\":1181.681},{\"x\":380.971,\"y\":1167.736},{\"x\":367.026,\"y\":1144.029},{\"x\":351.222,\"y\":1135.662},{\"x\":349.827,\"y\":1110.096},{\"x\":329.375,\"y\":1100.8},{\"x\":304.274,\"y\":1106.378},{\"x\":301.95,\"y\":1125.436},{\"x\":287.54,\"y\":1123.112},{\"x\":287.54,\"y\":1110.096},{\"x\":295.442,\"y\":1091.503},{\"x\":304.274,\"y\":1066.402},{\"x\":379.577,\"y\":1062.683},{\"x\":406.537,\"y\":1064.543},{\"x\":423.271,\"y\":1064.543},{\"x\":427.92,\"y\":1093.362},{\"x\":438.611,\"y\":1121.252},{\"x\":434.892,\"y\":1143.099},{\"x\":426.525,\"y\":1161.693}],\"texture\":\"assets/terrains/deepterrain.png\"},{\"id\":169,\"type\":\"Ter\",\"layerId\":\"islands\",\"points\":[{\"x\":420.017,\"y\":1230.023},{\"x\":407.467,\"y\":1234.207},{\"x\":397.705,\"y\":1245.363},{\"x\":400.03,\"y\":1271.394},{\"x\":399.565,\"y\":1302.073},{\"x\":382.366,\"y\":1308.58},{\"x\":356.8,\"y\":1308.58},{\"x\":353.546,\"y\":1297.424},{\"x\":347.503,\"y\":1269.999},{\"x\":338.671,\"y\":1248.152},{\"x\":324.726,\"y\":1241.179},{\"x\":294.977,\"y\":1254.66},{\"x\":285.216,\"y\":1280.225},{\"x\":285.216,\"y\":1307.651},{\"x\":294.512,\"y\":1333.217},{\"x\":354.476,\"y\":1334.611},{\"x\":418.623,\"y\":1330.892},{\"x\":427.92,\"y\":1315.553},{\"x\":455.81,\"y\":1318.807},{\"x\":468.36,\"y\":1309.51},{\"x\":454.88,\"y\":1295.1},{\"x\":427.92,\"y\":1290.917},{\"x\":421.877,\"y\":1276.042},{\"x\":432.103,\"y\":1230.023}],\"texture\":\"assets/terrains/deepterrain.png\"},{\"id\":170,\"type\":\"Ter\",\"layerId\":\"islands\",\"points\":[{\"x\":302.879,\"y\":1204.458},{\"x\":363.772,\"y\":1217.008},{\"x\":354.011,\"y\":1199.809},{\"x\":332.164,\"y\":1181.216},{\"x\":314.035,\"y\":1161.228},{\"x\":293.583,\"y\":1159.369},{\"x\":275.454,\"y\":1169.13},{\"x\":287.54,\"y\":1190.513}],\"texture\":\"assets/terrains/deepterrain.png\"},{\"id\":171,\"type\":\"Ter\",\"layerId\":\"islands\",\"points\":[{\"x\":257.326,\"y\":1063.613},{\"x\":228.971,\"y\":1062.683},{\"x\":197.362,\"y\":1054.781},{\"x\":165.288,\"y\":1056.64},{\"x\":132.75,\"y\":1062.683},{\"x\":126.242,\"y\":1080.812},{\"x\":126.707,\"y\":1103.124},{\"x\":129.496,\"y\":1139.846},{\"x\":125.313,\"y\":1175.638},{\"x\":129.961,\"y\":1210.036},{\"x\":130.891,\"y\":1236.996},{\"x\":128.102,\"y\":1270.464},{\"x\":124.383,\"y\":1310.905},{\"x\":129.031,\"y\":1334.146},{\"x\":154.132,\"y\":1352.275},{\"x\":175.515,\"y\":1369.938},{\"x\":196.432,\"y\":1344.837},{\"x\":221.998,\"y\":1340.189},{\"x\":248.029,\"y\":1331.357},{\"x\":247.564,\"y\":1316.483},{\"x\":237.802,\"y\":1297.889},{\"x\":240.592,\"y\":1277.901},{\"x\":246.634,\"y\":1261.632},{\"x\":227.576,\"y\":1257.449},{\"x\":218.279,\"y\":1268.14},{\"x\":211.772,\"y\":1287.663},{\"x\":192.714,\"y\":1303.002},{\"x\":175.515,\"y\":1306.256},{\"x\":151.343,\"y\":1305.327},{\"x\":144.371,\"y\":1282.55},{\"x\":144.836,\"y\":1246.757},{\"x\":154.132,\"y\":1210.965},{\"x\":175.515,\"y\":1193.302},{\"x\":196.897,\"y\":1183.075},{\"x\":216.42,\"y\":1197.485},{\"x\":227.576,\"y\":1230.488},{\"x\":240.127,\"y\":1242.109},{\"x\":248.494,\"y\":1238.855},{\"x\":251.283,\"y\":1212.36},{\"x\":245.24,\"y\":1184.47},{\"x\":233.619,\"y\":1167.736},{\"x\":208.518,\"y\":1162.158},{\"x\":217.35,\"y\":1148.677},{\"x\":241.056,\"y\":1147.748},{\"x\":246.17,\"y\":1131.943},{\"x\":242.451,\"y\":1119.858},{\"x\":244.31,\"y\":1098.94},{\"x\":254.072,\"y\":1076.628}],\"texture\":\"assets/terrains/coldterrain.png\"},{\"id\":173,\"type\":\"Ter\",\"layerId\":\"islands\",\"points\":[{\"x\":669.474,\"y\":359.891},{\"x\":746.499,\"y\":361.088},{\"x\":731.333,\"y\":368.671},{\"x\":706.989,\"y\":371.465},{\"x\":678.254,\"y\":366.675}],\"texture\":\"assets/terrains/terrain.png\"},{\"id\":174,\"type\":\"Ter\",\"layerId\":\"islands\",\"points\":[{\"x\":1073.548,\"y\":336.102},{\"x\":1063.802,\"y\":373.459},{\"x\":1065.427,\"y\":418.937},{\"x\":1074.089,\"y\":458.46},{\"x\":1092.497,\"y\":456.294},{\"x\":1139.058,\"y\":454.67},{\"x\":1197.53,\"y\":456.294},{\"x\":1205.651,\"y\":454.129},{\"x\":1205.651,\"y\":442.218},{\"x\":1200.237,\"y\":422.727},{\"x\":1180.746,\"y\":389.701},{\"x\":1161.797,\"y\":372.376},{\"x\":1127.688,\"y\":366.962},{\"x\":1097.37,\"y\":351.261}],\"texture\":\"assets/terrains/terrain.png\"},{\"id\":175,\"type\":\"Ter\",\"layerId\":\"islands\",\"points\":[{\"x\":1073.006,\"y\":193.17},{\"x\":1101.701,\"y\":192.629},{\"x\":1133.644,\"y\":186.673},{\"x\":1186.702,\"y\":190.463},{\"x\":1160.173,\"y\":179.635},{\"x\":1142.848,\"y\":174.221},{\"x\":1110.363,\"y\":169.348},{\"x\":1085.459,\"y\":174.762},{\"x\":1019.948,\"y\":176.928},{\"x\":1049.184,\"y\":193.17}],\"texture\":\"assets/terrains/beach.png\"},{\"id\":176,\"type\":\"Ter\",\"layerId\":\"islands\",\"points\":[{\"x\":1264.64,\"y\":196.692},{\"x\":1289.864,\"y\":192.277},{\"x\":1328.33,\"y\":196.061},{\"x\":1355.446,\"y\":193.539},{\"x\":1396.434,\"y\":185.341},{\"x\":1354.815,\"y\":175.882},{\"x\":1321.393,\"y\":175.882},{\"x\":1263.379,\"y\":179.666},{\"x\":1240.047,\"y\":188.494}],\"texture\":\"assets/terrains/swamp/island.png\"},{\"id\":177,\"type\":\"Ter\",\"layerId\":\"islands\",\"points\":[{\"x\":1257.073,\"y\":451.452},{\"x\":1258.964,\"y\":423.075},{\"x\":1250.136,\"y\":389.654},{\"x\":1265.27,\"y\":365.061},{\"x\":1304.367,\"y\":353.71},{\"x\":1321.393,\"y\":319.027},{\"x\":1329.591,\"y\":280.561},{\"x\":1347.248,\"y\":271.733},{\"x\":1358.599,\"y\":269.841},{\"x\":1369.949,\"y\":290.02},{\"x\":1370.58,\"y\":327.225},{\"x\":1389.498,\"y\":348.035},{\"x\":1409.677,\"y\":344.251},{\"x\":1424.811,\"y\":334.161},{\"x\":1434.27,\"y\":348.035},{\"x\":1428.595,\"y\":365.061},{\"x\":1404.632,\"y\":384.609},{\"x\":1379.408,\"y\":397.221},{\"x\":1366.166,\"y\":419.292},{\"x\":1364.274,\"y\":443.885},{\"x\":1351.662,\"y\":467.217},{\"x\":1312.565,\"y\":461.542},{\"x\":1284.819,\"y\":470.37},{\"x\":1257.073,\"y\":482.982}],\"texture\":\"assets/terrains/swamp/island.png\"},{\"id\":178,\"type\":\"Ter\",\"layerId\":\"islands\",\"points\":[{\"x\":1065.311,\"y\":1216.957},{\"x\":1075.538,\"y\":1222.535},{\"x\":1099.244,\"y\":1265.765},{\"x\":1128.529,\"y\":1281.569},{\"x\":1165.251,\"y\":1294.585},{\"x\":1195,\"y\":1300.163},{\"x\":1212.664,\"y\":1308.065},{\"x\":1212.664,\"y\":1335.49},{\"x\":1141.079,\"y\":1340.603},{\"x\":1091.342,\"y\":1355.013},{\"x\":1056.015,\"y\":1347.576},{\"x\":1046.718,\"y\":1324.799},{\"x\":1049.972,\"y\":1274.597},{\"x\":1058.339,\"y\":1226.719},{\"x\":1051.831,\"y\":1216.957}],\"texture\":\"assets/terrains/deepterrain.png\"},{\"id\":179,\"type\":\"Ter\",\"layerId\":\"islands\",\"points\":[{\"x\":1114.427,\"y\":1213.045},{\"x\":1132.555,\"y\":1220.017},{\"x\":1198.562,\"y\":1223.271},{\"x\":1192.984,\"y\":1203.283},{\"x\":1143.711,\"y\":1189.803},{\"x\":1108.849,\"y\":1208.861}],\"texture\":\"assets/terrains/deepterrain.png\"},{\"id\":180,\"type\":\"Ter\",\"layerId\":\"islands\",\"points\":[{\"x\":1056.322,\"y\":1177.252},{\"x\":1043.307,\"y\":1132.164},{\"x\":1055.858,\"y\":1102.879},{\"x\":1053.533,\"y\":1072.665},{\"x\":1067.014,\"y\":1061.044},{\"x\":1096.298,\"y\":1061.974},{\"x\":1137.203,\"y\":1065.692},{\"x\":1209.253,\"y\":1066.622},{\"x\":1201.815,\"y\":1086.145},{\"x\":1209.718,\"y\":1110.781},{\"x\":1199.956,\"y\":1142.855},{\"x\":1183.687,\"y\":1145.644},{\"x\":1162.305,\"y\":1141.46},{\"x\":1149.754,\"y\":1127.515},{\"x\":1126.047,\"y\":1124.726},{\"x\":1106.524,\"y\":1136.812},{\"x\":1089.326,\"y\":1152.616},{\"x\":1078.17,\"y\":1176.788}],\"texture\":\"assets/terrains/deepterrain.png\"},{\"id\":181,\"type\":\"Ter\",\"layerId\":\"islands\",\"points\":[{\"x\":1176.971,\"y\":1270.288},{\"x\":1193.213,\"y\":1269.747},{\"x\":1203.5,\"y\":1261.626},{\"x\":1189.965,\"y\":1257.836}],\"texture\":\"assets/terrains/deepterrain.png\"},{\"id\":182,\"type\":\"Ter\",\"layerId\":\"islands\",\"points\":[{\"x\":1258.724,\"y\":1060.763},{\"x\":1284.711,\"y\":1066.178},{\"x\":1320.986,\"y\":1060.222},{\"x\":1348.597,\"y\":1054.808},{\"x\":1363.757,\"y\":1062.929},{\"x\":1384.33,\"y\":1071.592},{\"x\":1419.522,\"y\":1083.503},{\"x\":1419.522,\"y\":1098.662},{\"x\":1408.152,\"y\":1111.656},{\"x\":1389.203,\"y\":1117.611},{\"x\":1368.629,\"y\":1113.821},{\"x\":1354.011,\"y\":1119.777},{\"x\":1351.846,\"y\":1139.268},{\"x\":1335.604,\"y\":1140.35},{\"x\":1309.616,\"y\":1140.35},{\"x\":1287.96,\"y\":1126.815},{\"x\":1268.469,\"y\":1107.866},{\"x\":1251.144,\"y\":1104.076},{\"x\":1243.564,\"y\":1088.917}],\"texture\":\"assets/terrains/swamp/island.png\"},{\"id\":183,\"type\":\"Ter\",\"layerId\":\"islands\",\"points\":[{\"x\":1248.978,\"y\":1335.257},{\"x\":1242.481,\"y\":1309.27},{\"x\":1256.558,\"y\":1301.69},{\"x\":1282.546,\"y\":1295.734},{\"x\":1319.361,\"y\":1293.569},{\"x\":1346.973,\"y\":1287.072},{\"x\":1357.801,\"y\":1287.072},{\"x\":1355.636,\"y\":1333.092},{\"x\":1343.183,\"y\":1349.875},{\"x\":1309.616,\"y\":1354.206},{\"x\":1294.998,\"y\":1349.875},{\"x\":1260.348,\"y\":1341.213}],\"texture\":\"assets/terrains/swamp/island.png\"},{\"id\":184,\"type\":\"Ter\",\"layerId\":\"islands\",\"points\":[{\"x\":1331.814,\"y\":1252.422},{\"x\":1352.929,\"y\":1257.836},{\"x\":1392.451,\"y\":1258.919},{\"x\":1416.815,\"y\":1249.173},{\"x\":1428.726,\"y\":1234.014},{\"x\":1408.152,\"y\":1229.683},{\"x\":1380.54,\"y\":1227.517},{\"x\":1362.674,\"y\":1235.097},{\"x\":1337.769,\"y\":1235.097},{\"x\":1308.533,\"y\":1237.804},{\"x\":1289.584,\"y\":1247.549}],\"texture\":\"assets/terrains/swamp/island.png\"},{\"id\":172,\"type\":\"Air\",\"layerId\":\"air-pockets\",\"points\":[{\"x\":302.361,\"y\":1121.391},{\"x\":350.618,\"y\":1121.862},{\"x\":353.018,\"y\":1104.27},{\"x\":326.635,\"y\":1091.592},{\"x\":300.936,\"y\":1100.158}],\"texture\":\"assets/terrains/deepterrain.png\",\"borderColor\":12763842},{\"id\":143,\"type\":\"Bg\",\"layerId\":\"background-terrains\",\"points\":[{\"x\":851.768,\"y\":345.827},{\"x\":875.731,\"y\":347.088},{\"x\":877.622,\"y\":335.738},{\"x\":874.469,\"y\":317.45},{\"x\":886.451,\"y\":299.794},{\"x\":900.324,\"y\":263.85},{\"x\":902.216,\"y\":253.76},{\"x\":871.317,\"y\":263.85},{\"x\":836.003,\"y\":269.525},{\"x\":830.958,\"y\":290.335},{\"x\":837.895,\"y\":299.163},{\"x\":836.003,\"y\":323.126},{\"x\":827.805,\"y\":354.025}],\"texture\":\"assets/terrains/terrain.png\",\"opacity\":0.6},{\"id\":90,\"type\":\"Wat\",\"layerId\":\"water\",\"points\":[{\"x\":143.927,\"y\":195.894},{\"x\":425.032,\"y\":195.894},{\"x\":425.032,\"y\":459.585},{\"x\":143.927,\"y\":459.585}],\"texture\":\"18943|12763842\",\"colors\":[18943,12763842],\"hasBorder\":false},{\"id\":91,\"type\":\"Wat\",\"layerId\":\"water\",\"points\":[{\"x\":644.44,\"y\":183.456},{\"x\":925.545,\"y\":183.456},{\"x\":925.545,\"y\":447.147},{\"x\":644.44,\"y\":447.147}],\"texture\":\"18943|38911\",\"colors\":[18943,38911],\"hasBorder\":false},{\"id\":92,\"type\":\"Wat\",\"layerId\":\"water\",\"points\":[{\"x\":1075.561,\"y\":183.865},{\"x\":1356.666,\"y\":183.865},{\"x\":1356.666,\"y\":447.556},{\"x\":1075.561,\"y\":447.556}],\"texture\":\"18943|697088\",\"colors\":[18943,697088],\"hasBorder\":false},{\"id\":93,\"type\":\"Wat\",\"layerId\":\"water\",\"points\":[{\"x\":146.908,\"y\":631.234},{\"x\":428.013,\"y\":631.234},{\"x\":428.013,\"y\":894.925},{\"x\":146.908,\"y\":894.925}],\"texture\":\"12763842|16777215\",\"colors\":[12763842,16777215],\"hasBorder\":false},{\"id\":94,\"type\":\"Wat\",\"layerId\":\"water\",\"points\":[{\"x\":646.927,\"y\":623.771},{\"x\":928.032,\"y\":623.771},{\"x\":928.032,\"y\":887.462},{\"x\":646.927,\"y\":887.462}],\"texture\":\"5000268|5000268\",\"colors\":[5000268,5000268],\"hasBorder\":false},{\"id\":95,\"type\":\"Wat\",\"layerId\":\"water\",\"points\":[{\"x\":1086.234,\"y\":626.259},{\"x\":1367.339,\"y\":626.259},{\"x\":1367.339,\"y\":889.95},{\"x\":1086.234,\"y\":889.95}],\"texture\":\"697088|1113856\",\"colors\":[697088,1113856],\"hasBorder\":false},{\"id\":96,\"type\":\"Wat\",\"layerId\":\"water\",\"points\":[{\"x\":136.958,\"y\":1066.574},{\"x\":418.063,\"y\":1066.574},{\"x\":418.063,\"y\":1330.265},{\"x\":136.958,\"y\":1330.265}],\"texture\":\"12763842|0\",\"colors\":[12763842,0],\"hasBorder\":false},{\"id\":97,\"type\":\"Wat\",\"layerId\":\"water\",\"points\":[{\"x\":644.934,\"y\":1066.574},{\"x\":926.039,\"y\":1066.574},{\"x\":926.039,\"y\":1330.265},{\"x\":644.934,\"y\":1330.265}],\"texture\":\"0|4605510\",\"colors\":[0,4605510],\"hasBorder\":false},{\"id\":98,\"type\":\"Wat\",\"layerId\":\"water\",\"points\":[{\"x\":1065.842,\"y\":1069.062},{\"x\":1346.947,\"y\":1069.062},{\"x\":1346.947,\"y\":1332.753},{\"x\":1065.842,\"y\":1332.753}],\"texture\":\"697088|0\",\"colors\":[697088,0],\"hasBorder\":false},{\"id\":99,\"type\":\"Wat\",\"layerId\":\"water\",\"points\":[{\"x\":53.302,\"y\":1421.084},{\"x\":1465.28,\"y\":1421.084},{\"x\":1465.28,\"y\":1474.263},{\"x\":53.302,\"y\":1474.263}],\"texture\":\"15991039|8126584\",\"colors\":[15991039,8126584],\"hasBorder\":false},{\"id\":100,\"type\":\"Wat\",\"layerId\":\"water\",\"points\":[{\"x\":427.385,\"y\":720.597},{\"x\":649.267,\"y\":720.597},{\"x\":649.267,\"y\":766.44},{\"x\":427.385,\"y\":766.44}],\"texture\":\"15991039|8126584\",\"colors\":[15991039,8126584],\"hasBorder\":false},{\"id\":101,\"type\":\"Wat\",\"layerId\":\"water\",\"points\":[{\"x\":924.328,\"y\":722.43},{\"x\":1087.53,\"y\":722.43},{\"x\":1087.53,\"y\":766.44},{\"x\":924.328,\"y\":764.606}],\"texture\":\"15991039|8126584\",\"colors\":[15991039,8126584],\"hasBorder\":false},{\"id\":102,\"type\":\"Wat\",\"layerId\":\"water\",\"points\":[{\"x\":1204.89,\"y\":627.076},{\"x\":1258.068,\"y\":627.076},{\"x\":1258.068,\"y\":445.536},{\"x\":1204.89,\"y\":445.536}],\"texture\":\"15991039|8126584\",\"colors\":[15991039,8126584],\"hasBorder\":false},{\"id\":103,\"type\":\"Wat\",\"layerId\":\"water\",\"points\":[{\"x\":1076.108,\"y\":336.053},{\"x\":922.494,\"y\":335.512},{\"x\":922.494,\"y\":293.336},{\"x\":1076.65,\"y\":294.419}],\"texture\":\"15991039|8126584\",\"colors\":[15991039,8126584],\"hasBorder\":false},{\"id\":104,\"type\":\"Wat\",\"layerId\":\"water\",\"points\":[{\"x\":643.766,\"y\":348.348},{\"x\":423.717,\"y\":348.348},{\"x\":423.717,\"y\":293.336},{\"x\":643.766,\"y\":293.336}],\"texture\":\"15991039|8126584\",\"colors\":[15991039,8126584],\"hasBorder\":false},{\"id\":105,\"type\":\"Wat\",\"layerId\":\"water\",\"points\":[{\"x\":247.678,\"y\":460.206},{\"x\":293.522,\"y\":460.206},{\"x\":293.522,\"y\":632.577},{\"x\":247.678,\"y\":632.577}],\"texture\":\"15991039|8126584\",\"colors\":[15991039,8126584],\"hasBorder\":false},{\"id\":106,\"type\":\"Wat\",\"layerId\":\"water\",\"points\":[{\"x\":256.847,\"y\":1067.173},{\"x\":302.691,\"y\":1067.173},{\"x\":302.691,\"y\":894.802},{\"x\":256.847,\"y\":894.802}],\"texture\":\"15991039|8126584\",\"colors\":[15991039,8126584],\"hasBorder\":false},{\"id\":107,\"type\":\"Wat\",\"layerId\":\"water\",\"points\":[{\"x\":647.433,\"y\":1230.376},{\"x\":418.216,\"y\":1230.376},{\"x\":418.216,\"y\":1190.033},{\"x\":647.433,\"y\":1188.2}],\"texture\":\"15991039|8126584\",\"colors\":[15991039,8126584],\"hasBorder\":false},{\"id\":108,\"type\":\"Wat\",\"layerId\":\"water\",\"points\":[{\"x\":755.624,\"y\":1067.173},{\"x\":801.467,\"y\":1067.173},{\"x\":801.467,\"y\":885.633},{\"x\":755.624,\"y\":885.633}],\"texture\":\"15991039|8126584\",\"colors\":[15991039,8126584],\"hasBorder\":false},{\"id\":109,\"type\":\"Wat\",\"layerId\":\"water\",\"points\":[{\"x\":925.723,\"y\":1177.197},{\"x\":1065.525,\"y\":1177.197},{\"x\":1065.525,\"y\":1216.993},{\"x\":925.902,\"y\":1216.243}],\"texture\":\"15991039|8126584\",\"colors\":[15991039,8126584],\"hasBorder\":false},{\"id\":110,\"type\":\"Wat\",\"layerId\":\"water\",\"points\":[{\"x\":1210.391,\"y\":1069.007},{\"x\":1258.068,\"y\":1069.007},{\"x\":1258.068,\"y\":891.134},{\"x\":1210.391,\"y\":891.134}],\"texture\":\"15991039|8126584\",\"colors\":[15991039,8126584],\"hasBorder\":false},{\"id\":111,\"type\":\"Wat\",\"layerId\":\"water\",\"points\":[{\"x\":984.841,\"y\":1424.752},{\"x\":1023.349,\"y\":1424.752},{\"x\":1023.349,\"y\":293.336},{\"x\":984.841,\"y\":293.336}],\"texture\":\"15991039|8126584\",\"colors\":[15991039,8126584],\"hasBorder\":false},{\"id\":112,\"type\":\"Wat\",\"layerId\":\"water\",\"points\":[{\"x\":502.568,\"y\":1426.586},{\"x\":548.411,\"y\":1426.586},{\"x\":550.245,\"y\":293.336},{\"x\":509.903,\"y\":293.336}],\"texture\":\"15991039|8126584\",\"colors\":[15991039,8126584],\"hasBorder\":false},{\"id\":113,\"type\":\"Wat\",\"layerId\":\"water\",\"points\":[{\"x\":764.967,\"y\":448.455},{\"x\":805.309,\"y\":448.455},{\"x\":805.309,\"y\":629.995},{\"x\":764.967,\"y\":629.995}],\"texture\":\"15991039|8126584\",\"colors\":[15991039,8126584],\"hasBorder\":false},{\"id\":114,\"type\":\"Sky\",\"layerId\":\"sky\",\"points\":[{\"x\":0,\"y\":0},{\"x\":1500,\"y\":0},{\"x\":1500,\"y\":1500},{\"x\":0,\"y\":1500}],\"texture\":\"9699520|4849761\",\"colors\":[9699520,4849761]}],\"worldSize\":{\"width\":\"150\",\"height\":\"150\"}}",
  "public": true,
  "locked": false,
  "clonable": false,
  "permissions": 1,
  "likes": 0,
  "objects": 99,
  "created_at": "2019-08-30T23:29:04.000Z",
  "updated_at": "2019-08-31T17:48:54.000Z",
  "deleted_at": null,
  "user": {
    "id": 594916,
    "username": "MemeSnorfer",
    "description": "S N O R F",
    "about": null,
    "team_id": null,
    "team_role": null,
    "date_created": "2019-05-18T18:42:06.000Z",
    "date_last_played": "2020-11-10T03:30:18.000Z",
    "kill_count": 4269,
    "play_count": 84,
    "highest_score": 2776159,
    "picture": "594916.jpg",
    "displayPicture": true,
    "active": true,
    "ban_message": null,
    "ban_at": null,
    "coins": 111,
    "tier": 1,
    "xp": 0,
    "migrated": false,
    "verified": false,
    "beta": false
  },
  "tags": [],
  "packs": [
    {
      "id": 1,
      "name": "Original",
      "user_id": null,
      "cost": 0,
      "spritesheets": 2,
      "version": 15,
      "created_at": "2019-09-08T22:58:58.000Z",
      "updated_at": "2019-09-08T22:58:58.000Z"
    },
    {
      "id": 2,
      "name": "FllllSH",
      "user_id": null,
      "cost": 0,
      "spritesheets": 1,
      "version": 1,
      "created_at": "2019-10-03T00:41:18.000Z",
      "updated_at": "2019-10-03T00:41:18.000Z"
    },
    {
      "id": 3,
      "name": "Pathos",
      "user_id": null,
      "cost": 0,
      "spritesheets": 3,
      "version": 2,
      "created_at": "2019-10-02T22:58:18.000Z",
      "updated_at": "2019-10-02T22:58:18.000Z"
    },
    {
      "id": 10,
      "name": "Pathos #2",
      "user_id": null,
      "cost": 0,
      "spritesheets": 3,
      "version": 1,
      "created_at": "2019-10-11T21:58:37.000Z",
      "updated_at": "2019-10-11T21:58:37.000Z"
    }
  ],
  "archived_at": "2025-05-08T19:23:59.940Z"
}